intergrated/__init__.py
integrated-0.0.0.dist-info/METADATA
integrated-0.0.0.dist-info/WHEEL
integrated-0.0.0.dist-info/top_level.txt
integrated-0.0.0.dist-info/RECORD
