Metadata-Version: 2.2
Name: integrated
Version: 0.0.0
Summary: Coming soon
Author-email: Wiktor Tomczak <wiktor.tomczak@gmail.com>
